bandage/__init__.py
bandage-1.2.dist-info/LICENSE
bandage-1.2.dist-info/METADATA
bandage-1.2.dist-info/WHEEL
bandage-1.2.dist-info/top_level.txt
bandage-1.2.dist-info/RECORD
