Metadata-Version: 2.1
Name: bandage
Version: 1.2
Summary: Patching library.
Home-page: https://github.com/perpetualCreations/bandage/
Author: perpetualCreations
Author-email: tchen0584@gmail.com
License: MIT
Platform: UNKNOWN
Classifier: Programming Language :: Python :: 3
Classifier: License :: OSI Approved :: MIT License
Classifier: Operating System :: OS Independent
Requires-Python: >=3.6
Requires-Dist: urllib3
